{
  "result_id": "magnetic_dipole_moment",
  "result_name": "Magnetic Dipole Moment",
  "result_equations": [
    {
      "id": "magnetic_dipole_current_loop",
      "equation": "vec mu = I*vec A"
    },
    {
      "id": "potential_energy_magnetic_field",
      "equation": "U = -vec mu cdot vec B"
    },
    {
      "id": "torque_on_magnetic_dipole",
      "equation": "vec tau = vec mu times vec B"
    },
    {
      "id": "magnetic_field_dipole",
      "equation": "vec B = (mu_0/(4*pi)) * (3*(vec mu cdot hat r)*hat r - vec mu)/r^3"
    }
  ],
  "explanation": "A magnetic dipole moment characterizes the magnetic strength and orientation of a current loop or magnetic object. It arises from circulating currents and determines how the system interacts with external magnetic fields through torques and potential energies. Magnetic dipoles are fundamental to understanding atomic magnetism, magnetic materials, magnetic resonance, and the behavior of permanent magnets and electromagnets.",
  "equations_assumptions": [
    {
      "id": "eq_assump1",
      "text": "The current loop is small compared to distances of interest (dipole approximation)."
    },
    {
      "id": "eq_assump2",
      "text": "Steady currents (no time-varying fields)."
    },
    {
      "id": "eq_assump3",
      "text": "Linear, isotropic, and homogeneous medium (or vacuum)."
    },
    {
      "id": "eq_assump4",
      "text": "Far-field approximation for magnetic field calculation."
    }
  ],
  "definitions": [
    {
      "symbol": "vec mu",
      "definition": "Magnetic dipole moment vector."
    },
    {
      "symbol": "I",
      "definition": "Current in the loop."
    },
    {
      "symbol": "vec A",
      "definition": "Area vector of the current loop (magnitude = area, direction by right-hand rule)."
    },
    {
      "symbol": "U",
      "definition": "Potential energy of magnetic dipole in external field."
    },
    {
      "symbol": "vec B",
      "definition": "External magnetic field."
    },
    {
      "symbol": "vec tau",
      "definition": "Torque on the magnetic dipole."
    },
    {
      "symbol": "mu_0",
      "definition": "Permeability of free space (4π × 10⁻⁷ H/m)."
    },
    {
      "symbol": "hat r",
      "definition": "Unit vector from dipole to field point."
    },
    {
      "symbol": "r",
      "definition": "Distance from dipole to field point."
    }
  ],
  "derivation": [
    {
      "step": 1,
      "equation": "text(Magnetic dipole moment from current loop)"
    },
    {
      "step": 2,
      "equation": "vec mu = I*int d vec A = I*vec A"
    },
    {
      "step": 3,
      "equation": "text(Potential energy in external field)"
    },
    {
      "step": 4,
      "equation": "U = -int vec J cdot vec A_ext dV"
    },
    {
      "step": 5,
      "equation": "text(For uniform field: ) vec A_ext = (1/2)*vec B times vec r"
    },
    {
      "step": 6,
      "equation": "U = -vec mu cdot vec B"
    },
    {
      "step": 7,
      "equation": "text(Torque from potential energy)"
    },
    {
      "step": 8,
      "equation": "vec tau = -nabla U = -nabla(-vec mu cdot vec B)"
    },
    {
      "step": 9,
      "equation": "vec tau = vec mu times vec B"
    },
    {
      "step": 10,
      "equation": "text(Magnetic field of dipole from vector potential)"
    },
    {
      "step": 11,
      "equation": "vec A(vec r) = (mu_0/(4*pi)) * (vec mu times vec r)/r^3"
    },
    {
      "step": 12,
      "equation": "vec B = nabla times vec A"
    },
    {
      "step": 13,
      "equation": "vec B = (mu_0/(4*pi)) * (3*(vec mu cdot hat r)*hat r - vec mu)/r^3"
    }
  ],
  "derivation_assumptions": [
    {
      "id": "assumption1",
      "text": "The current distribution is localized (dipole approximation valid)."
    },
    {
      "id": "assumption2",
      "text": "Magnetostatic conditions (∂B/∂t = 0)."
    },
    {
      "id": "assumption3",
      "text": "Far-field limit (r >> size of current distribution)."
    },
    {
      "id": "assumption4",
      "text": "Linear superposition of fields applies."
    }
  ],
  "derivation_explanation": [
    {
      "step": 1,
      "text": "Define magnetic dipole moment for a current loop."
    },
    {
      "step": 2,
      "text": "Integrate current times area element to get total magnetic moment."
    },
    {
      "step": 3,
      "text": "Calculate potential energy of current distribution in external field."
    },
    {
      "step": 4,
      "text": "Use the interaction energy between current and vector potential."
    },
    {
      "step": 5,
      "text": "For uniform magnetic field, express vector potential in terms of B."
    },
    {
      "step": 6,
      "text": "Simplify to get the dipole-field interaction energy."
    },
    {
      "step": 7,
      "text": "Calculate torque as negative gradient of potential energy."
    },
    {
      "step": 8,
      "text": "Apply the gradient operator to the interaction energy."
    },
    {
      "step": 9,
      "text": "Obtain the torque as cross product of dipole moment and field."
    },
    {
      "step": 10,
      "text": "Calculate the magnetic field produced by the dipole itself."
    },
    {
      "step": 11,
      "text": "Start with the vector potential of a magnetic dipole."
    },
    {
      "step": 12,
      "text": "Take the curl of vector potential to get magnetic field."
    },
    {
      "step": 13,
      "text": "Evaluate the curl to get the dipole field expression."
    }
  ],
  "programmatic_verification": {
    "language": "python 3.11.12",
    "library": "sympy 1.12.0",
    "code": [
      "import sympy as sp",
      "import math",
      "",
      "# Define symbols",
      "I, A, B, mu, theta, r = sp.symbols('I A B mu theta r', real=True, positive=True)",
      "mu_0 = sp.symbols('mu_0', positive=True, real=True)",
      "",
      "# Magnetic dipole moment",
      "mu_magnitude = I * A",
      "",
      "# Potential energy",
      "U = -mu * B * sp.cos(theta)  # θ is angle between μ and B",
      "",
      "# Torque magnitude",
      "tau_magnitude = mu * B * sp.sin(theta)",
      "",
      "# Test with realistic values",
      "# Current loop: I = 1 A, radius = 1 cm",
      "I_val = 1.0        # A",
      "radius = 0.01      # m",
      "A_val = math.pi * radius**2  # m²",
      "mu_val = I_val * A_val       # A⋅m²",
      "",
      "# Magnetic field: B = 0.1 T",
      "B_val = 0.1        # T",
      "",
      "# Test potential energy for different orientations",
      "# Parallel (θ = 0): minimum energy",
      "U_parallel = -mu_val * B_val",
      "# Antiparallel (θ = π): maximum energy",
      "U_antiparallel = mu_val * B_val",
      "# Perpendicular (θ = π/2): zero energy",
      "U_perpendicular = 0",
      "",
      "assert U_parallel < U_perpendicular < U_antiparallel, 'Energy ordering incorrect'",
      "",
      "# Test torque for different orientations",
      "# Parallel (θ = 0): zero torque",
      "tau_parallel = 0",
      "# Perpendicular (θ = π/2): maximum torque",
      "tau_perpendicular = mu_val * B_val",
      "# Antiparallel (θ = π): zero torque",
      "tau_antiparallel = 0",
      "",
      "assert tau_perpendicular > tau_parallel and tau_perpendicular > tau_antiparallel, 'Torque maximum at perpendicular'",
      "",
      "# Test magnetic field of dipole",
      "# On axis (θ = 0): B = (μ₀/4π) * (2μ/r³)",
      "# In equatorial plane (θ = π/2): B = (μ₀/4π) * (μ/r³)",
      "mu_0_val = 4*math.pi*1e-7  # H/m",
      "r_val = 0.1                # m (10 cm from dipole)",
      "",
      "B_axis = (mu_0_val/(4*math.pi)) * (2*mu_val) / r_val**3",
      "B_equatorial = (mu_0_val/(4*math.pi)) * mu_val / r_val**3",
      "",
      "# Axial field should be twice the equatorial field",
      "ratio = B_axis / B_equatorial",
      "assert abs(ratio - 2.0) < 1e-10, 'Axial field should be 2x equatorial field'",
      "",
      "# Test units: magnetic dipole moment [μ] = A⋅m²",
      "# Torque [τ] = [μ][B] = A⋅m²⋅T = A⋅m²⋅(kg/(A⋅s²)) = kg⋅m²/s² = J",
      "",
      "# Test relationship with angular momentum for electron",
      "# μ = (e/2m)L where L is angular momentum",
      "# This is the gyromagnetic ratio for orbital motion",
      "",
      "# Test diamagnetic vs paramagnetic behavior",
      "# Diamagnetic: μ opposes B (negative susceptibility)",
      "# Paramagnetic: μ aligns with B (positive susceptibility)",
      "",
      "# For a circular current loop in external field,",
      "# induced current opposes field change (Lenz's law)",
      "",
      "# Test magnetic moment of current-carrying coil",
      "N_turns = 100  # number of turns",
      "mu_coil = N_turns * I_val * A_val",
      "expected_mu_coil = N_turns * mu_val",
      "assert abs(mu_coil - expected_mu_coil) < 1e-10, 'Multi-turn coil moment incorrect'"
    ]
  },
  "domain": "physics.class-ph",
  "theory_status": "current",
  "validity_regime": {
    "conditions": [
      "Magnetostatic conditions (steady currents)",
      "Dipole approximation (small current loops)",
      "Far-field for external field calculations",
      "Linear, homogeneous media"
    ],
    "limitations": [
      "Near-field effects for close distances",
      "Time-varying fields require full Maxwell equations",
      "Quantum effects in atomic/molecular magnetism",
      "Nonlinear magnetic materials"
    ]
  },
  "historical_context": {
    "importance": "Fundamental concept for understanding magnetism from atomic scale to macroscopic magnets, essential for magnetic materials and devices",
    "development_period": "1820s-1860s",
    "key_insights": [
      "André-Marie Ampère showed equivalence of current loops and magnets",
      "Led to understanding of atomic magnetism",
      "Foundation for magnetic material properties",
      "Essential for magnetic resonance and quantum mechanics"
    ]
  },
  "references": [
    {
      "id": "R1",
      "citation": "Griffiths, D. J. (2017). *Introduction to Electrodynamics* (4th ed.). Cambridge University Press."
    },
    {
      "id": "R2",
      "citation": "Jackson, J. D. (1998). *Classical Electrodynamics* (3rd ed.). Wiley."
    }
  ],
  "dependencies": [
    "magnetic_field",
    "amperes_law"
  ],
  "created_by": "Synthetic entry, AI created. May have mistakes, looking for contributors to this entry.",
  "review_status": "draft"
}